scantree/__init__.py
scantree/_filter.py
scantree/_node.py
scantree/_path.py
scantree/_scan.py
scantree/_version.py
scantree/compat.py
scantree/test_utils.py
scantree-0.0.3.dist-info/LICENSE
scantree-0.0.3.dist-info/METADATA
scantree-0.0.3.dist-info/WHEEL
scantree-0.0.3.dist-info/top_level.txt
scantree-0.0.3.dist-info/RECORD
