Metadata-Version: 2.1
Name: scantree
Version: 0.0.3
Summary: Flexible recursive directory iterator: scandir meets glob("**", recursive=True)
Home-page: https://github.com/andhus/scantree
Author: Anders Huss
Author-email: andhus@kth.se
License: MIT
Requires-Python: >=3.8
License-File: LICENSE
Requires-Dist: attrs >=18.0.0
Requires-Dist: pathspec >=0.10.1
